{
  "id": "395009",
  "name": "TRPG",
  "font_family": "iconfont",
  "css_prefix_text": "icon-",
  "description": "",
  "glyphs": [
    {
      "icon_id": "7683684",
      "name": "back",
      "font_class": "back",
      "unicode": "e61a",
      "unicode_decimal": 58906
    },
    {
      "icon_id": "7683690",
      "name": "close",
      "font_class": "close",
      "unicode": "e622",
      "unicode_decimal": 58914
    },
    {
      "icon_id": "566215",
      "name": "警告",
      "font_class": "jinggao",
      "unicode": "e616",
      "unicode_decimal": 58902
    },
    {
      "icon_id": "544893",
      "name": "paintbrush",
      "font_class": "paintbrush",
      "unicode": "e8b4",
      "unicode_decimal": 59572
    },
    {
      "icon_id": "1174292",
      "name": "pointer",
      "font_class": "pointer",
      "unicode": "e65c",
      "unicode_decimal": 58972
    },
    {
      "icon_id": "5127474",
      "name": "rectangle",
      "font_class": "rectangle",
      "unicode": "e7f9",
      "unicode_decimal": 59385
    },
    {
      "icon_id": "5940735",
      "name": "polygon",
      "font_class": "polygon",
      "unicode": "e614",
      "unicode_decimal": 58900
    },
    {
      "icon_id": "10104425",
      "name": "ruler",
      "font_class": "ruler",
      "unicode": "e6f2",
      "unicode_decimal": 59122
    },
    {
      "icon_id": "5317143",
      "name": "hand",
      "font_class": "hand",
      "unicode": "e766",
      "unicode_decimal": 59238
    },
    {
      "icon_id": "996183",
      "name": "view",
      "font_class": "view",
      "unicode": "e613",
      "unicode_decimal": 58899
    },
    {
      "icon_id": "2743880",
      "name": "附件",
      "font_class": "fujian",
      "unicode": "e640",
      "unicode_decimal": 58944
    },
    {
      "icon_id": "2546709",
      "name": "预览",
      "font_class": "yulan",
      "unicode": "e6a2",
      "unicode_decimal": 59042
    },
    {
      "icon_id": "4685706",
      "name": "下载",
      "font_class": "Group-",
      "unicode": "e688",
      "unicode_decimal": 59016
    },
    {
      "icon_id": "3841095",
      "name": "edit",
      "font_class": "edit",
      "unicode": "e612",
      "unicode_decimal": 58898
    },
    {
      "icon_id": "3066735",
      "name": "截图",
      "font_class": "jietu",
      "unicode": "e615",
      "unicode_decimal": 58901
    },
    {
      "icon_id": "3391765",
      "name": "htb－Arrow right02",
      "font_class": "htbarrowright02",
      "unicode": "e60f",
      "unicode_decimal": 58895
    },
    {
      "icon_id": "700957",
      "name": "switch",
      "font_class": "switch",
      "unicode": "e9b7",
      "unicode_decimal": 59831
    },
    {
      "icon_id": "1196879",
      "name": "folder",
      "font_class": "folder",
      "unicode": "e62f",
      "unicode_decimal": 58927
    },
    {
      "icon_id": "4767566",
      "name": "属性文件",
      "font_class": "o-property",
      "unicode": "e6e9",
      "unicode_decimal": 59113
    },
    {
      "icon_id": "4099965",
      "name": "QQ",
      "font_class": "QQ",
      "unicode": "e786",
      "unicode_decimal": 59270
    },
    {
      "icon_id": "4199325",
      "name": "分享",
      "font_class": "fenxiang",
      "unicode": "e63c",
      "unicode_decimal": 58940
    },
    {
      "icon_id": "2827210",
      "name": "htb－Arrow right02",
      "font_class": "forward",
      "unicode": "e60e",
      "unicode_decimal": 58894
    },
    {
      "icon_id": "250890",
      "name": "好友",
      "font_class": "personal",
      "unicode": "e60d",
      "unicode_decimal": 58893
    },
    {
      "icon_id": "1212178",
      "name": "会话",
      "font_class": "huihua",
      "unicode": "e769",
      "unicode_decimal": 59241
    },
    {
      "icon_id": "2789205",
      "name": "smile",
      "font_class": "smile",
      "unicode": "e683",
      "unicode_decimal": 59011
    },
    {
      "icon_id": "669452",
      "name": "最小化",
      "font_class": "zuixiaohua1",
      "unicode": "e657",
      "unicode_decimal": 58967
    },
    {
      "icon_id": "651000",
      "name": "关闭",
      "font_class": "guanbi",
      "unicode": "e610",
      "unicode_decimal": 58896
    },
    {
      "icon_id": "1107345",
      "name": "最大化",
      "font_class": "group12",
      "unicode": "e60c",
      "unicode_decimal": 58892
    },
    {
      "icon_id": "1845778",
      "name": "最小化",
      "font_class": "zuixiaohua",
      "unicode": "e618",
      "unicode_decimal": 58904
    },
    {
      "icon_id": "1140579",
      "name": "开发",
      "font_class": "kaifa",
      "unicode": "e6bb",
      "unicode_decimal": 59067
    },
    {
      "icon_id": "389068",
      "name": "loading",
      "font_class": "loading",
      "unicode": "eb0f",
      "unicode_decimal": 60175
    },
    {
      "icon_id": "2537797",
      "name": "通过",
      "font_class": "tongguo",
      "unicode": "e66b",
      "unicode_decimal": 58987
    },
    {
      "icon_id": "2565985",
      "name": "拒绝",
      "font_class": "jujue",
      "unicode": "e680",
      "unicode_decimal": 59008
    },
    {
      "icon_id": "2050884",
      "name": "鸽子",
      "font_class": "gezi",
      "unicode": "e648",
      "unicode_decimal": 58952
    },
    {
      "icon_id": "3054019",
      "name": "cthulhu",
      "font_class": "cthulhu",
      "unicode": "e60b",
      "unicode_decimal": 58891
    },
    {
      "icon_id": "411628",
      "name": "性别保密",
      "font_class": "xingbiebaomi",
      "unicode": "e617",
      "unicode_decimal": 58903
    },
    {
      "icon_id": "717802",
      "name": "性别",
      "font_class": "xingbie",
      "unicode": "e727",
      "unicode_decimal": 59175
    },
    {
      "icon_id": "1080706",
      "name": "男",
      "font_class": "nan",
      "unicode": "e698",
      "unicode_decimal": 59032
    },
    {
      "icon_id": "1146114",
      "name": "女",
      "font_class": "nv",
      "unicode": "e64a",
      "unicode_decimal": 58954
    },
    {
      "icon_id": "1944183",
      "name": "系统消息",
      "font_class": "xitongxiaoxi",
      "unicode": "e608",
      "unicode_decimal": 58888
    },
    {
      "icon_id": "12832",
      "name": "下",
      "font_class": "xia",
      "unicode": "e606",
      "unicode_decimal": 58886
    },
    {
      "icon_id": "2197073",
      "name": "任务模版创建人",
      "font_class": "chuangjianren",
      "unicode": "e61d",
      "unicode_decimal": 58909
    },
    {
      "icon_id": "1280552",
      "name": "文档",
      "font_class": "wendang",
      "unicode": "e621",
      "unicode_decimal": 58913
    },
    {
      "icon_id": "1502781",
      "name": "地图",
      "font_class": "ditu",
      "unicode": "e6d7",
      "unicode_decimal": 59095
    },
    {
      "icon_id": "1444389",
      "name": "dice-d4",
      "font_class": "dice-d",
      "unicode": "e6fa",
      "unicode_decimal": 59130
    },
    {
      "icon_id": "1444391",
      "name": "dice-d8",
      "font_class": "dice-d1",
      "unicode": "e6fb",
      "unicode_decimal": 59131
    },
    {
      "icon_id": "1444392",
      "name": "dice-d6",
      "font_class": "dice-d2",
      "unicode": "e6fc",
      "unicode_decimal": 59132
    },
    {
      "icon_id": "1444394",
      "name": "dice-d20",
      "font_class": "dice-d3",
      "unicode": "e6fd",
      "unicode_decimal": 59133
    },
    {
      "icon_id": "1962763",
      "name": "info",
      "font_class": "info",
      "unicode": "e611",
      "unicode_decimal": 58897
    },
    {
      "icon_id": "2532930",
      "name": "群组",
      "font_class": "icon",
      "unicode": "e603",
      "unicode_decimal": 58883
    },
    {
      "icon_id": "312379",
      "name": "添加组",
      "font_class": "weibiaoti102",
      "unicode": "e61c",
      "unicode_decimal": 58908
    },
    {
      "icon_id": "240468",
      "name": "编辑",
      "font_class": "bianji",
      "unicode": "e83f",
      "unicode_decimal": 59455
    },
    {
      "icon_id": "1376015",
      "name": "删除",
      "font_class": "shanchu",
      "unicode": "e76b",
      "unicode_decimal": 59243
    },
    {
      "icon_id": "1650426",
      "name": "搜索",
      "font_class": "sousuo",
      "unicode": "e60a",
      "unicode_decimal": 58890
    },
    {
      "icon_id": "2340628",
      "name": "我的群组",
      "font_class": "wodequnzu",
      "unicode": "e958",
      "unicode_decimal": 59736
    },
    {
      "icon_id": "1287702",
      "name": "已发送",
      "font_class": "yifasong",
      "unicode": "e62e",
      "unicode_decimal": 58926
    },
    {
      "icon_id": "2097113",
      "name": "同意",
      "font_class": "dui",
      "unicode": "e67d",
      "unicode_decimal": 59005
    },
    {
      "icon_id": "565857",
      "name": "对",
      "font_class": "duiconverted",
      "unicode": "e620",
      "unicode_decimal": 58912
    },
    {
      "icon_id": "610618",
      "name": "loading",
      "font_class": "jishi",
      "unicode": "e61e",
      "unicode_decimal": 58910
    },
    {
      "icon_id": "33704",
      "name": "重置",
      "font_class": "zhongzhi",
      "unicode": "e67c",
      "unicode_decimal": 59004
    },
    {
      "icon_id": "1647504",
      "name": "保存",
      "font_class": "baocun",
      "unicode": "e634",
      "unicode_decimal": 58932
    },
    {
      "icon_id": "1218853",
      "name": "编辑",
      "font_class": "bianji2",
      "unicode": "e602",
      "unicode_decimal": 58882
    },
    {
      "icon_id": "1550133",
      "name": "引用",
      "font_class": "yinyong",
      "unicode": "e605",
      "unicode_decimal": 58885
    },
    {
      "icon_id": "2012603",
      "name": "引用",
      "font_class": "yinyong1",
      "unicode": "e601",
      "unicode_decimal": 58881
    },
    {
      "icon_id": "1145067",
      "name": "icon_tbar_add",
      "font_class": "icon-tbar-add",
      "unicode": "e604",
      "unicode_decimal": 58884
    },
    {
      "icon_id": "1296213",
      "name": "云盘_30",
      "font_class": "yunpan",
      "unicode": "e623",
      "unicode_decimal": 58915
    },
    {
      "icon_id": "727744",
      "name": "more",
      "font_class": "more",
      "unicode": "e600",
      "unicode_decimal": 58880
    },
    {
      "icon_id": "1312816",
      "name": "more",
      "font_class": "jiahao",
      "unicode": "e64b",
      "unicode_decimal": 58955
    },
    {
      "icon_id": "424359",
      "name": "骰子游戏",
      "font_class": "21466",
      "unicode": "e631",
      "unicode_decimal": 58929
    },
    {
      "icon_id": "2753312",
      "name": "骰子",
      "font_class": "pinrenpinkongxin",
      "unicode": "e609",
      "unicode_decimal": 58889
    },
    {
      "icon_id": "393310",
      "name": "talk",
      "font_class": "talk",
      "unicode": "e61f",
      "unicode_decimal": 58911
    },
    {
      "icon_id": "1340576",
      "name": "普通",
      "font_class": "putong",
      "unicode": "e72d",
      "unicode_decimal": 59181
    },
    {
      "icon_id": "2570664",
      "name": "动作冒c险",
      "font_class": "dongzuomaocxian",
      "unicode": "e619",
      "unicode_decimal": 58905
    },
    {
      "icon_id": "1781123",
      "name": "out",
      "font_class": "yunxiangmugongdanweixintubiao-",
      "unicode": "e64d",
      "unicode_decimal": 58957
    },
    {
      "icon_id": "494582",
      "name": "笔记本",
      "font_class": "bijiben",
      "unicode": "e624",
      "unicode_decimal": 58916
    },
    {
      "icon_id": "582179",
      "name": "卡信息",
      "font_class": "qiaxinxi",
      "unicode": "e61b",
      "unicode_decimal": 58907
    },
    {
      "icon_id": "758551",
      "name": "消息",
      "font_class": "xiaoxi",
      "unicode": "e63e",
      "unicode_decimal": 58942
    },
    {
      "icon_id": "1024824",
      "name": "close_48",
      "font_class": "close48",
      "unicode": "e70c",
      "unicode_decimal": 59148
    },
    {
      "icon_id": "2087465",
      "name": "联系人",
      "font_class": "lianxiren",
      "unicode": "e607",
      "unicode_decimal": 58887
    }
  ]
}
